{
    "cmdList": [
        {
            "messageId": 1118,
            "body": {
                "type": "Buffer",
                "data": [
                    10,
                    39,
                    10,
                    0,
                    16,
                    18,
                    26,
                    26,
                    10,
                    24,
                    8,
                    180,
                    243,
                    245,
                    156,
                    253,
                    255,
                    255,
                    255,
                    255,
                    1,
                    18,
                    11,
                    16,
                    170,
                    195,
                    154,
                    199,
                    252,
                    255,
                    255,
                    255,
                    255,
                    1,
                    32,
                    143,
                    132,
                    128,
                    16,
                    40,
                    2
                ]
            }
        },
        {
            "messageId": 1118,
            "body": {
                "type": "Buffer",
                "data": [
                    10,
                    31,
                    10,
                    0,
                    16,
                    18,
                    26,
                    18,
                    10,
                    16,
                    8,
                    180,
                    253,
                    200,
                    141,
                    252,
                    255,
                    255,
                    255,
                    255,
                    1,
                    18,
                    3,
                    16,
                    135,
                    7,
                    32,
                    143,
                    132,
                    128,
                    16,
                    40,
                    2
                ]
            }
        },
        {
            "messageId": 359,
            "body": {
                "type": "Buffer",
                "data": [
                    10,
                    33,
                    8,
                    6,
                    16,
                    2,
                    26,
                    27,
                    8,
                    143,
                    132,
                    128,
                    16,
                    16,
                    180,
                    253,
                    200,
                    141,
                    252,
                    255,
                    255,
                    255,
                    255,
                    1,
                    24,
                    1,
                    34,
                    7,
                    8,
                    1,
                    29,
                    0,
                    192,
                    97,
                    68
                ]
            }
        },
        {
            "messageId": 1118,
            "body": {
                "type": "Buffer",
                "data": [
                    10,
                    39,
                    10,
                    0,
                    16,
                    18,
                    26,
                    26,
                    10,
                    24,
                    8,
                    180,
                    243,
                    245,
                    156,
                    253,
                    255,
                    255,
                    255,
                    255,
                    1,
                    18,
                    11,
                    16,
                    170,
                    195,
                    154,
                    199,
                    252,
                    255,
                    255,
                    255,
                    255,
                    1,
                    32,
                    142,
                    132,
                    128,
                    16,
                    40,
                    2
                ]
            }
        },
        {
            "messageId": 1118,
            "body": {
                "type": "Buffer",
                "data": [
                    10,
                    31,
                    10,
                    0,
                    16,
                    18,
                    26,
                    18,
                    10,
                    16,
                    8,
                    180,
                    253,
                    200,
                    141,
                    252,
                    255,
                    255,
                    255,
                    255,
                    1,
                    18,
                    3,
                    16,
                    135,
                    7,
                    32,
                    142,
                    132,
                    128,
                    16,
                    40,
                    2
                ]
            }
        },
        {
            "messageId": 359,
            "body": {
                "type": "Buffer",
                "data": [
                    10,
                    33,
                    8,
                    6,
                    16,
                    2,
                    26,
                    27,
                    8,
                    142,
                    132,
                    128,
                    16,
                    16,
                    180,
                    253,
                    200,
                    141,
                    252,
                    255,
                    255,
                    255,
                    255,
                    1,
                    24,
                    1,
                    34,
                    7,
                    8,
                    1,
                    29,
                    0,
                    192,
                    97,
                    68
                ]
            }
        }
    ]
}